RTL-Design/Week-03/rtl/Day-06_01_sync_fifo.sv
// =============================================================================
`timescale 1ns/1ps
// Module      : sync_fifo
// Description : Synchronous FIFO (single clock domain for both read and
//               write sides - Learning Topic 6.1). Memory array, write
//               pointer, read pointer, and the count register are all
//               updated in ONE always_ff block, per the assignment.
//               full/empty are derived COMBINATIONALLY from count
//               (Learning Topic 6.4 - raw wr_ptr==rd_ptr comparison alone
//               is ambiguous between "just reset" and "completely full",
//               so a count register is used instead, which is the simpler
//               of the two standard approaches).
// =============================================================================

module sync_fifo #(
    parameter int WIDTH = 8,
    parameter int DEPTH = 8
) (
    input  logic clk,
    input  logic rst_n,          // active-low asynchronous reset
    input  logic wr_en,
    input  logic rd_en,
    input  logic [WIDTH-1:0] din,
    output logic [WIDTH-1:0] dout,
    output logic full,
    output logic empty
);

    // Pointer width only needs to address DEPTH locations (0..DEPTH-1).
    localparam int PTR_WIDTH = $clog2(DEPTH);
    // Count must represent 0..DEPTH inclusive (DEPTH+1 possible values),
    // which needs one more bit than the pointers themselves - e.g. for
    // DEPTH=8, pointers are 3 bits (0-7) but count needs 4 bits (0-8).
    localparam int CNT_WIDTH = $clog2(DEPTH + 1);

    logic [WIDTH-1:0] mem [0:DEPTH-1];
    logic [PTR_WIDTH-1:0] wr_ptr, rd_ptr;
    logic [CNT_WIDTH-1:0] count;

    // full/empty - combinational, derived from count alone (not from
    // comparing wr_ptr to rd_ptr, which cannot distinguish full from empty
    // on its own - Learning Topic 6.4).
    assign full  = (count == DEPTH);
    assign empty = (count == 0);

    // Read data - combinational "peek" at the current front of the queue.
    // Design decision (documented explicitly, not left implicit - Day 7
    // principle): dout always shows mem[rd_ptr], regardless of rd_en. When
    // rd_en pulses (and the FIFO isn't empty), rd_ptr advances on the next
    // clock edge and dout will then show the NEXT entry. This keeps the
    // design to exactly the four registers the assignment specifies
    // (mem, wr_ptr, rd_ptr, count) with no separate output register.
    assign dout = mem[rd_ptr];

    // ---------------------------------------------------------------
    // Memory array, write pointer, read pointer, and count - all in
    // ONE always_ff block, per the assignment.
    //
    // Both wr_en and rd_en are individually qualified by !full / !empty
    // BEFORE deciding which case applies. This is what correctly handles
    // every combination automatically, including the trickier ones:
    //   - write while full            -> blocked (data would be lost)
    //   - read while empty            -> blocked (undefined data)
    //   - simultaneous read+write     -> count unchanged, both proceed
    //   - simultaneous read+write,
    //     but FIFO is full            -> only the read proceeds (frees a
    //                                    slot; the write is still blocked
    //                                    since there was no room BEFORE
    //                                    this cycle's read takes effect)
    //   - simultaneous read+write,
    //     but FIFO is empty           -> only the write proceeds
    // ---------------------------------------------------------------
    always_ff @(posedge clk or negedge rst_n) begin
        if (!rst_n) begin
            wr_ptr <= '0;
            rd_ptr <= '0;
            count  <= '0;
        end else begin
            case ({wr_en && !full, rd_en && !empty})
                2'b10: begin  // write only
                    mem[wr_ptr] <= din;
                    wr_ptr <= (wr_ptr == DEPTH - 1) ? '0 : wr_ptr + 1'b1;
                    count  <= count + 1'b1;
                end
                2'b01: begin  // read only
                    rd_ptr <= (rd_ptr == DEPTH - 1) ? '0 : rd_ptr + 1'b1;
                    count  <= count - 1'b1;
                end
                2'b11: begin  // simultaneous read + write - count unchanged
                    mem[wr_ptr] <= din;
                    wr_ptr <= (wr_ptr == DEPTH - 1) ? '0 : wr_ptr + 1'b1;
                    rd_ptr <= (rd_ptr == DEPTH - 1) ? '0 : rd_ptr + 1'b1;
                end
                default: begin  // 2'b00 - no valid operation this cycle
                    // explicit empty branch (not left as an implicit
                    // "do nothing") so nothing is inferred as a latch
                end
            endcase
        end
    end

endmodule

RTL-Design/Week-03/tb/Day-06_03_sync_fifo_multiwrap_tb.sv
// =============================================================================
`timescale 1ns/1ps
// Testbench   : sync_fifo_multiwrap_tb
// Purpose     : Regression test closing ISSUE-D7-02. Runs THREE consecutive
//               fill-then-drain cycles back to back (instead of just one),
//               so both wr_ptr and rd_ptr wrap around the DEPTH boundary
//               multiple times in a row. Checks data integrity across every
//               wrap, not just the first one - a systematic addressing bug
//               at the wrap point could plausibly only surface on a SECOND
//               or THIRD wrap if the first one happened to mask it.
// =============================================================================

module sync_fifo_multiwrap_tb;

    localparam int WIDTH = 8;
    localparam int DEPTH = 8;

    logic clk, rst_n;
    logic wr_en, rd_en;
    logic [WIDTH-1:0] din;
    logic [WIDTH-1:0] dout;
    logic full, empty;

    int cycle;
    int errors;
    logic [WIDTH-1:0] expected_q[$];  // software reference queue (scoreboard-style)
    logic [WIDTH-1:0] expected_val;

    sync_fifo #(.WIDTH(WIDTH), .DEPTH(DEPTH)) dut (
        .clk(clk), .rst_n(rst_n), .wr_en(wr_en), .rd_en(rd_en),
        .din(din), .dout(dout), .full(full), .empty(empty)
    );

    initial begin
        $dumpfile("dump.vcd");
        $dumpvars(0, sync_fifo_multiwrap_tb);
    end

    initial clk = 0;
    always #5 clk = ~clk;

    task automatic do_write(input [7:0] val);
        wr_en = 1; rd_en = 0; din = val;
        @(negedge clk);
        expected_q.push_back(val);
        cycle++;
    endtask

    task automatic do_read();
        logic [WIDTH-1:0] captured;
        wr_en = 0; rd_en = 1; din = '0;
        captured = dout;  // combinational peek BEFORE the clock edge - this is the value this read actually consumes
        @(negedge clk);
        expected_val = expected_q.pop_front();
        if (captured !== expected_val) begin
            $display("  MISMATCH at cycle %0d: read_value=%0h expected=%0h", cycle, captured, expected_val);
            errors++;
        end
        cycle++;
    endtask

    initial begin
        errors = 0;
        cycle = 1;
        wr_en = 0; rd_en = 0; din = '0;
        rst_n = 0;
        @(negedge clk);
        @(negedge clk);
        rst_n = 1;

        $display("Running 3 consecutive fill-then-drain cycles (24 writes, 24 reads total)...");

        for (int loop = 0; loop < 3; loop++) begin
            // Fill to full - use a different value range each loop so a
            // stale-data bug from a PREVIOUS wrap would be obvious
            for (int i = 0; i < DEPTH; i++) begin
                do_write(8'(loop * 8'h20 + i));
            end
            // Drain to empty, checking every value against the reference queue
            for (int i = 0; i < DEPTH; i++) begin
                do_read();
            end
        end

        wr_en = 0; rd_en = 0;
        @(negedge clk);

        if (errors == 0)
            $display("PASS: all 24 reads across 3 wraps matched the reference queue exactly.");
        else
            $display("FAIL: %0d mismatch(es) found.", errors);

        $display("Multi-wrap regression test complete.");
        $finish;
    end

endmodule

RTL-Design/Week-03/vvp and vcd and wave/d6_multiwrap.vcd
$date
	Mon Aug 17 20:55:22 2026
$end
$version
	Icarus Verilog
$end
$timescale
	1ps
$end
$scope module sync_fifo_multiwrap_tb $end
$var wire 1 ! full $end
$var wire 1 " empty $end
$var wire 8 # dout [7:0] $end
$var parameter 32 $ DEPTH $end
$var parameter 32 % WIDTH $end
$var reg 1 & clk $end
$var reg 8 ' din [7:0] $end
$var reg 8 ( expected_val [7:0] $end
$var reg 1 ) rd_en $end
$var reg 1 * rst_n $end
$var reg 1 + wr_en $end
$var integer 32 , cycle [31:0] $end
$var integer 32 - errors [31:0] $end
$scope module dut $end
$var wire 1 & clk $end
$var wire 8 . din [7:0] $end
$var wire 8 / dout [7:0] $end
$var wire 1 ) rd_en $end
$var wire 1 * rst_n $end
$var wire 1 + wr_en $end
$var wire 1 ! full $end
$var wire 1 " empty $end
$var parameter 32 0 CNT_WIDTH $end
$var parameter 32 1 DEPTH $end
$var parameter 32 2 PTR_WIDTH $end
$var parameter 32 3 WIDTH $end
$var reg 4 4 count [3:0] $end
$var reg 3 5 rd_ptr [2:0] $end
$var reg 3 6 wr_ptr [2:0] $end
$upscope $end
$scope begin $ivl_for_loop0 $end
$var integer 32 7 loop [31:0] $end
$scope begin $ivl_for_loop1 $end
$var integer 32 8 i [31:0] $end
$upscope $end
$scope begin $ivl_for_loop2 $end
$var integer 32 9 i [31:0] $end
$upscope $end
$upscope $end
$scope task do_read $end
$upscope $end
$scope task do_write $end
$upscope $end
$upscope $end
$enddefinitions $end
$comment Show the parameter values. $end
$dumpall
b1000 3
b11 2
b1000 1
b100 0
b1000 %
b1000 $
$end
#0
$dumpvars
b0 9
b0 8
b0 7
b0 6
b0 5
b0 4
bx /
b0 .
b0 -
b1 ,
0+
0*
0)
bx (
b0 '
0&
bx #
1"
0!
$end
#5000
1&
#10000
0&
#15000
1&
#20000
1+
1*
0&
#25000
0"
b1 4
b1 6
b0 #
b0 /
1&
#30000
b1 '
b1 .
b1 8
b10 ,
0&
#35000
b10 4
b10 6
1&
#40000
b10 '
b10 .
b10 8
b11 ,
0&
#45000
b11 4
b11 6
1&
#50000
b11 '
b11 .
b11 8
b100 ,
0&
#55000
b100 4
b100 6
1&
#60000
b100 '
b100 .
b100 8
b101 ,
0&
#65000
b101 4
b101 6
1&
#70000
b101 '
b101 .
b101 8
b110 ,
0&
#75000
b110 4
b110 6
1&
#80000
b110 '
b110 .
b110 8
b111 ,
0&
#85000
b111 4
b111 6
1&
#90000
b111 '
b111 .
b111 8
b1000 ,
0&
#95000
1!
b1000 4
b0 6
1&
#100000
b0 '
b0 .
1)
0+
b1000 8
b1001 ,
0&
#105000
0!
b111 4
b1 #
b1 /
b1 5
1&
#110000
b1 9
b1010 ,
b0 (
0&
#115000
b110 4
b10 #
b10 /
b10 5
1&
#120000
b10 9
b1011 ,
b1 (
0&
#125000
b101 4
b11 #
b11 /
b11 5
1&
#130000
b11 9
b1100 ,
b10 (
0&
#135000
b100 4
b100 #
b100 /
b100 5
1&
#140000
b100 9
b1101 ,
b11 (
0&
#145000
b11 4
b101 #
b101 /
b101 5
1&
#150000
b101 9
b1110 ,
b100 (
0&
#155000
b10 4
b110 #
b110 /
b110 5
1&
#160000
b110 9
b1111 ,
b101 (
0&
#165000
b1 4
b111 #
b111 /
b111 5
1&
#170000
b111 9
b10000 ,
b110 (
0&
#175000
1"
b0 4
b0 #
b0 /
b0 5
1&
#180000
b100000 '
b100000 .
0)
1+
b0 8
b1 7
b1000 9
b10001 ,
b111 (
0&
#185000
0"
b1 4
b1 6
b100000 #
b100000 /
1&
#190000
b100001 '
b100001 .
b1 8
b10010 ,
0&
#195000
b10 4
b10 6
1&
#200000
b100010 '
b100010 .
b10 8
b10011 ,
0&
#205000
b11 4
b11 6
1&
#210000
b100011 '
b100011 .
b11 8
b10100 ,
0&
#215000
b100 4
b100 6
1&
#220000
b100100 '
b100100 .
b100 8
b10101 ,
0&
#225000
b101 4
b101 6
1&
#230000
b100101 '
b100101 .
b101 8
b10110 ,
0&
#235000
b110 4
b110 6
1&
#240000
b100110 '
b100110 .
b110 8
b10111 ,
0&
#245000
b111 4
b111 6
1&
#250000
b100111 '
b100111 .
b111 8
b11000 ,
0&
#255000
1!
b1000 4
b0 6
1&
#260000
b0 '
b0 .
1)
0+
b0 9
b1000 8
b11001 ,
0&
#265000
0!
b111 4
b100001 #
b100001 /
b1 5
1&
#270000
b1 9
b11010 ,
b100000 (
0&
#275000
b110 4
b100010 #
b100010 /
b10 5
1&
#280000
b10 9
b11011 ,
b100001 (
0&
#285000
b101 4
b100011 #
b100011 /
b11 5
1&
#290000
b11 9
b11100 ,
b100010 (
0&
#295000
b100 4
b100100 #
b100100 /
b100 5
1&
#300000
b100 9
b11101 ,
b100011 (
0&
#305000
b11 4
b100101 #
b100101 /
b101 5
1&
#310000
b101 9
b11110 ,
b100100 (
0&
#315000
b10 4
b100110 #
b100110 /
b110 5
1&
#320000
b110 9
b11111 ,
b100101 (
0&
#325000
b1 4
b100111 #
b100111 /
b111 5
1&
#330000
b111 9
b100000 ,
b100110 (
0&
#335000
1"
b0 4
b100000 #
b100000 /
b0 5
1&
#340000
b1000000 '
b1000000 .
0)
1+
b0 8
b10 7
b1000 9
b100001 ,
b100111 (
0&
#345000
0"
b1 4
b1 6
b1000000 #
b1000000 /
1&
#350000
b1000001 '
b1000001 .
b1 8
b100010 ,
0&
#355000
b10 4
b10 6
1&
#360000
b1000010 '
b1000010 .
b10 8
b100011 ,
0&
#365000
b11 4
b11 6
1&
#370000
b1000011 '
b1000011 .
b11 8
b100100 ,
0&
#375000
b100 4
b100 6
1&
#380000
b1000100 '
b1000100 .
b100 8
b100101 ,
0&
#385000
b101 4
b101 6
1&
#390000
b1000101 '
b1000101 .
b101 8
b100110 ,
0&
#395000
b110 4
b110 6
1&
#400000
b1000110 '
b1000110 .
b110 8
b100111 ,
0&
#405000
b111 4
b111 6
1&
#410000
b1000111 '
b1000111 .
b111 8
b101000 ,
0&
#415000
1!
b1000 4
b0 6
1&
#420000
b0 '
b0 .
1)
0+
b0 9
b1000 8
b101001 ,
0&
#425000
0!
b111 4
b1000001 #
b1000001 /
b1 5
1&
#430000
b1 9
b101010 ,
b1000000 (
0&
#435000
b110 4
b1000010 #
b1000010 /
b10 5
1&
#440000
b10 9
b101011 ,
b1000001 (
0&
#445000
b101 4
b1000011 #
b1000011 /
b11 5
1&
#450000
b11 9
b101100 ,
b1000010 (
0&
#455000
b100 4
b1000100 #
b1000100 /
b100 5
1&
#460000
b100 9
b101101 ,
b1000011 (
0&
#465000
b11 4
b1000101 #
b1000101 /
b101 5
1&
#470000
b101 9
b101110 ,
b1000100 (
0&
#475000
b10 4
b1000110 #
b1000110 /
b110 5
1&
#480000
b110 9
b101111 ,
b1000101 (
0&
#485000
b1 4
b1000111 #
b1000111 /
b111 5
1&
#490000
b111 9
b110000 ,
b1000110 (
0&
#495000
1"
b0 4
b1000000 #
b1000000 /
b0 5
1&
#500000
0)
b11 7
b1000 9
b110001 ,
b1000111 (
0&
