RTL-Design/Week-03/rtl/Day-06_01_sync_fifo.sv
// =============================================================================
`timescale 1ns/1ps
// Module      : sync_fifo
// Description : Synchronous FIFO (single clock domain for both read and
//               write sides - Learning Topic 6.1). Memory array, write
//               pointer, read pointer, and the count register are all
//               updated in ONE always_ff block, per the assignment.
//               full/empty are derived COMBINATIONALLY from count
//               (Learning Topic 6.4 - raw wr_ptr==rd_ptr comparison alone
//               is ambiguous between "just reset" and "completely full",
//               so a count register is used instead, which is the simpler
//               of the two standard approaches).
// =============================================================================

module sync_fifo #(
    parameter int WIDTH = 8,
    parameter int DEPTH = 8
) (
    input  logic clk,
    input  logic rst_n,          // active-low asynchronous reset
    input  logic wr_en,
    input  logic rd_en,
    input  logic [WIDTH-1:0] din,
    output logic [WIDTH-1:0] dout,
    output logic full,
    output logic empty
);

    // Pointer width only needs to address DEPTH locations (0..DEPTH-1).
    localparam int PTR_WIDTH = $clog2(DEPTH);
    // Count must represent 0..DEPTH inclusive (DEPTH+1 possible values),
    // which needs one more bit than the pointers themselves - e.g. for
    // DEPTH=8, pointers are 3 bits (0-7) but count needs 4 bits (0-8).
    localparam int CNT_WIDTH = $clog2(DEPTH + 1);

    logic [WIDTH-1:0] mem [0:DEPTH-1];
    logic [PTR_WIDTH-1:0] wr_ptr, rd_ptr;
    logic [CNT_WIDTH-1:0] count;

    // full/empty - combinational, derived from count alone (not from
    // comparing wr_ptr to rd_ptr, which cannot distinguish full from empty
    // on its own - Learning Topic 6.4).
    assign full  = (count == DEPTH);
    assign empty = (count == 0);

    // Read data - combinational "peek" at the current front of the queue.
    // Design decision (documented explicitly, not left implicit - Day 7
    // principle): dout always shows mem[rd_ptr], regardless of rd_en. When
    // rd_en pulses (and the FIFO isn't empty), rd_ptr advances on the next
    // clock edge and dout will then show the NEXT entry. This keeps the
    // design to exactly the four registers the assignment specifies
    // (mem, wr_ptr, rd_ptr, count) with no separate output register.
    assign dout = mem[rd_ptr];

    // ---------------------------------------------------------------
    // Memory array, write pointer, read pointer, and count - all in
    // ONE always_ff block, per the assignment.
    //
    // Both wr_en and rd_en are individually qualified by !full / !empty
    // BEFORE deciding which case applies. This is what correctly handles
    // every combination automatically, including the trickier ones:
    //   - write while full            -> blocked (data would be lost)
    //   - read while empty            -> blocked (undefined data)
    //   - simultaneous read+write     -> count unchanged, both proceed
    //   - simultaneous read+write,
    //     but FIFO is full            -> only the read proceeds (frees a
    //                                    slot; the write is still blocked
    //                                    since there was no room BEFORE
    //                                    this cycle's read takes effect)
    //   - simultaneous read+write,
    //     but FIFO is empty           -> only the write proceeds
    // ---------------------------------------------------------------
    always_ff @(posedge clk or negedge rst_n) begin
        if (!rst_n) begin
            wr_ptr <= '0;
            rd_ptr <= '0;
            count  <= '0;
        end else begin
            case ({wr_en && !full, rd_en && !empty})
                2'b10: begin  // write only
                    mem[wr_ptr] <= din;
                    wr_ptr <= (wr_ptr == DEPTH - 1) ? '0 : wr_ptr + 1'b1;
                    count  <= count + 1'b1;
                end
                2'b01: begin  // read only
                    rd_ptr <= (rd_ptr == DEPTH - 1) ? '0 : rd_ptr + 1'b1;
                    count  <= count - 1'b1;
                end
                2'b11: begin  // simultaneous read + write - count unchanged
                    mem[wr_ptr] <= din;
                    wr_ptr <= (wr_ptr == DEPTH - 1) ? '0 : wr_ptr + 1'b1;
                    rd_ptr <= (rd_ptr == DEPTH - 1) ? '0 : rd_ptr + 1'b1;
                end
                default: begin  // 2'b00 - no valid operation this cycle
                    // explicit empty branch (not left as an implicit
                    // "do nothing") so nothing is inferred as a latch
                end
            endcase
        end
    end

endmodule

RTL-Design/Week-03/tb/Day-06_02_sync_fifo_smoke_tb.sv
// =============================================================================
`timescale 1ns/1ps
// Testbench   : sync_fifo_smoke_tb
// Purpose     : Required smoke sequence per the assignment:
//                 reset -> fill to full -> attempt one extra write (blocked)
//                 -> drain to empty -> attempt one extra read (blocked)
//               PLUS an added block specifically exercising simultaneous
//               read+write (while full, while partially filled, and while
//               empty) - the base sequence above never actually creates a
//               cycle where wr_en and rd_en are both asserted together, and
//               the assignment explicitly calls out "handle simultaneous
//               read+write - count must not change" as something to verify,
//               not just implement.
//               Prints wr_en / rd_en / din / dout / count / full / empty
//               every cycle. WIDTH=8, DEPTH=8 (assignment defaults).
// =============================================================================

module sync_fifo_smoke_tb;

    localparam int WIDTH = 8;
    localparam int DEPTH = 8;

    logic clk, rst_n;
    logic wr_en, rd_en;
    logic [WIDTH-1:0] din;
    logic [WIDTH-1:0] dout;
    logic full, empty;

    int cycle;

    sync_fifo #(.WIDTH(WIDTH), .DEPTH(DEPTH)) dut (
        .clk    (clk),
        .rst_n  (rst_n),
        .wr_en  (wr_en),
        .rd_en  (rd_en),
        .din    (din),
        .dout   (dout),
        .full   (full),
        .empty  (empty)
    );

    initial begin
        $dumpfile("dump.vcd");
        $dumpvars(0, sync_fifo_smoke_tb);
    end

    initial clk = 0;
    always #5 clk = ~clk;

    task automatic do_cycle(input string label);
        @(negedge clk);
        $display("%0t\t%0d\t%-20s\t%0b\t%0b\t%0h\t%0h\t%0d\t%0b\t%0b",
                  $time, cycle, label, wr_en, rd_en, din, dout,
                  dut.count, full, empty);
        cycle++;
    endtask

    initial begin
        $display("time\tcycle\tphase\t\t\twr\trd\tdin\tdout\tcount\tfull\tempty");
        cycle = 1;
        wr_en = 0; rd_en = 0; din = '0;

        // --- Reset ---
        rst_n = 0;
        @(negedge clk);
        @(negedge clk);
        rst_n = 1;

        // === REQUIRED SEQUENCE =========================================

        // --- Fill to full: 8 writes, din = 0x10..0x17 ---
        for (int i = 0; i < DEPTH; i++) begin
            wr_en = 1; rd_en = 0; din = 8'h10 + i[7:0];
            do_cycle("fill");
        end

        // --- Attempt one extra write while full (should be blocked) ---
        wr_en = 1; rd_en = 0; din = 8'hFF;  // poison value - must NOT appear later
        do_cycle("write-while-full");

        // === ADDED: simultaneous read+write coverage ====================
        // (not exercised by the base sequence above, but explicitly called
        // out in the assignment as something to "handle")

        // --- Simultaneous R+W while FULL: only the read should proceed;
        //     this write (0xA0) must NOT be stored, since there was no room
        //     BEFORE this cycle's read takes effect ---
        wr_en = 1; rd_en = 1; din = 8'hA0;
        do_cycle("simul-RW-while-full");

        // --- Simultaneous R+W while partially filled (count=7 now, neither
        //     full nor empty): BOTH should proceed, count unchanged ---
        wr_en = 1; rd_en = 1; din = 8'hA1;
        do_cycle("simul-RW-normal");

        wr_en = 0; rd_en = 0; din = '0;
        do_cycle("idle");

        // --- Drain the remaining 7 entries. Expected order: 0x12, 0x13,
        //     0x14, 0x15, 0x16, 0x17, then 0xA1 (the value written during
        //     the simultaneous R+W above) - confirming 0x10 (consumed
        //     earlier) and 0xFF (blocked, never stored) correctly never
        //     reappear ---
        for (int i = 0; i < 7; i++) begin
            wr_en = 0; rd_en = 1; din = '0;
            do_cycle("drain");
        end

        // --- Attempt one extra read while empty (should be blocked) ---
        wr_en = 0; rd_en = 1; din = '0;
        do_cycle("read-while-empty");

        // --- Simultaneous R+W while EMPTY: only the write should proceed;
        //     the read must be blocked (nothing valid to return) ---
        wr_en = 1; rd_en = 1; din = 8'hB0;
        do_cycle("simul-RW-while-empty");

        // --- Drain the final single entry (0xB0) to confirm it landed
        //     correctly and the FIFO returns to empty cleanly ---
        wr_en = 0; rd_en = 1; din = '0;
        do_cycle("final-drain");

        $display("Smoke test complete.");
        $finish;
    end

endmodule

RTL-Design/Week-03/vvp and vcd and wave/d6_smoke.vcd
$date
	Mon Aug 17 20:55:22 2026
$end
$version
	Icarus Verilog
$end
$timescale
	1ps
$end
$scope module sync_fifo_smoke_tb $end
$var wire 1 ! full $end
$var wire 1 " empty $end
$var wire 8 # dout [7:0] $end
$var parameter 32 $ DEPTH $end
$var parameter 32 % WIDTH $end
$var reg 1 & clk $end
$var reg 8 ' din [7:0] $end
$var reg 1 ( rd_en $end
$var reg 1 ) rst_n $end
$var reg 1 * wr_en $end
$var integer 32 + cycle [31:0] $end
$scope module dut $end
$var wire 1 & clk $end
$var wire 8 , din [7:0] $end
$var wire 8 - dout [7:0] $end
$var wire 1 ( rd_en $end
$var wire 1 ) rst_n $end
$var wire 1 * wr_en $end
$var wire 1 ! full $end
$var wire 1 " empty $end
$var parameter 32 . CNT_WIDTH $end
$var parameter 32 / DEPTH $end
$var parameter 32 0 PTR_WIDTH $end
$var parameter 32 1 WIDTH $end
$var reg 4 2 count [3:0] $end
$var reg 3 3 rd_ptr [2:0] $end
$var reg 3 4 wr_ptr [2:0] $end
$upscope $end
$scope begin $ivl_for_loop0 $end
$var integer 32 5 i [31:0] $end
$upscope $end
$scope begin $ivl_for_loop1 $end
$var integer 32 6 i [31:0] $end
$upscope $end
$scope task do_cycle $end
$upscope $end
$upscope $end
$enddefinitions $end
$comment Show the parameter values. $end
$dumpall
b1000 1
b11 0
b1000 /
b100 .
b1000 %
b1000 $
$end
#0
$dumpvars
b0 6
b0 5
b0 4
b0 3
b0 2
bx -
b0 ,
b1 +
0*
0)
0(
b0 '
0&
bx #
1"
0!
$end
#5000
1&
#10000
0&
#15000
1&
#20000
b10000 '
b10000 ,
1*
1)
0&
#25000
0"
b1 2
b1 4
b10000 #
b10000 -
1&
#30000
b10001 '
b10001 ,
b1 5
b10 +
0&
#35000
b10 2
b10 4
1&
#40000
b10010 '
b10010 ,
b10 5
b11 +
0&
#45000
b11 2
b11 4
1&
#50000
b10011 '
b10011 ,
b11 5
b100 +
0&
#55000
b100 2
b100 4
1&
#60000
b10100 '
b10100 ,
b100 5
b101 +
0&
#65000
b101 2
b101 4
1&
#70000
b10101 '
b10101 ,
b101 5
b110 +
0&
#75000
b110 2
b110 4
1&
#80000
b10110 '
b10110 ,
b110 5
b111 +
0&
#85000
b111 2
b111 4
1&
#90000
b10111 '
b10111 ,
b111 5
b1000 +
0&
#95000
1!
b1000 2
b0 4
1&
#100000
b11111111 '
b11111111 ,
b1000 5
b1001 +
0&
#105000
1&
#110000
b10100000 '
b10100000 ,
1(
b1010 +
0&
#115000
0!
b111 2
b10001 #
b10001 -
b1 3
1&
#120000
b10100001 '
b10100001 ,
b1011 +
0&
#125000
b10010 #
b10010 -
b10 3
b1 4
1&
#130000
b0 '
b0 ,
0(
0*
b1100 +
0&
#135000
1&
#140000
1(
b1101 +
0&
#145000
b110 2
b10011 #
b10011 -
b11 3
1&
#150000
b1 6
b1110 +
0&
#155000
b101 2
b10100 #
b10100 -
b100 3
1&
#160000
b10 6
b1111 +
0&
#165000
b100 2
b10101 #
b10101 -
b101 3
1&
#170000
b11 6
b10000 +
0&
#175000
b11 2
b10110 #
b10110 -
b110 3
1&
#180000
b100 6
b10001 +
0&
#185000
b10 2
b10111 #
b10111 -
b111 3
1&
#190000
b101 6
b10010 +
0&
#195000
b1 2
b10100001 #
b10100001 -
b0 3
1&
#200000
b110 6
b10011 +
0&
#205000
1"
b0 2
b10001 #
b10001 -
b1 3
1&
#210000
b111 6
b10100 +
0&
#215000
1&
#220000
b10110000 '
b10110000 ,
1*
b10101 +
0&
#225000
0"
b1 2
b10 4
b10110000 #
b10110000 -
1&
#230000
b0 '
b0 ,
0*
b10110 +
0&
#235000
1"
b0 2
b10010 #
b10010 -
b10 3
1&
#240000
b10111 +
0&
